ohme/__init__.py
ohme/const.py
ohme/ohme.py
ohme/py.typed
ohme/utils.py
ohme-1.6.0.dist-info/licenses/LICENSE
ohme-1.6.0.dist-info/METADATA
ohme-1.6.0.dist-info/WHEEL
ohme-1.6.0.dist-info/top_level.txt
ohme-1.6.0.dist-info/RECORD
