Metadata-Version: 2.4
Name: ohme
Version: 1.6.0
Summary: A Python wrapper for the Ohme API, used by the Home Assistant integration.
Author-email: Dan Raper <git@danr.uk>
License: MIT
Project-URL: Homepage, https://github.com/dan-r/ohmepy
Project-URL: Bug Tracker, https://github.com/dan-r/ohmepy/issues
Classifier: Programming Language :: Python :: 3
Classifier: Operating System :: OS Independent
Classifier: License :: OSI Approved :: MIT License
Requires-Python: >=3.7
License-File: LICENSE
Requires-Dist: aiohttp>=3.0.0
Dynamic: license-file
